airpilot_blackbox/__init__.py
airpilot_blackbox/analytics.py
airpilot_blackbox/cli.py
airpilot_blackbox/parser.py
airpilot_blackbox/pricing.py
airpilot_blackbox/pricing_fetcher.py
airpilot_blackbox-0.1.1.dist-info/METADATA
airpilot_blackbox-0.1.1.dist-info/WHEEL
airpilot_blackbox-0.1.1.dist-info/entry_points.txt
airpilot_blackbox-0.1.1.dist-info/licenses/LICENSE
airpilot_blackbox-0.1.1.dist-info/RECORD
