Metadata-Version: 2.4
Name: airpilot-blackbox
Version: 0.1.1
Summary: AirPilot Blackbox - Analyze Claude AI usage logs and calculate costs
Project-URL: Homepage, https://github.com/shaneholloman/airpilot-blackbox
Project-URL: Repository, https://github.com/shaneholloman/airpilot-blackbox
Project-URL: Issues, https://github.com/shaneholloman/airpilot-blackbox/issues
Author: shaneholloman
License-Expression: MIT
License-File: LICENSE
Keywords: ai,airpilot,analytics,blackbox,claude,cost-tracking,usage
Classifier: Development Status :: 4 - Beta
Classifier: Environment :: Console
Classifier: Intended Audience :: Developers
Classifier: License :: OSI Approved :: MIT License
Classifier: Programming Language :: Python :: 3
Classifier: Programming Language :: Python :: 3.8
Classifier: Programming Language :: Python :: 3.9
Classifier: Programming Language :: Python :: 3.10
Classifier: Programming Language :: Python :: 3.11
Classifier: Programming Language :: Python :: 3.12
Classifier: Topic :: Software Development :: Libraries :: Python Modules
Classifier: Topic :: Utilities
Requires-Python: >=3.8
Requires-Dist: click>=8.1.0
Requires-Dist: python-dateutil>=2.8.0
Requires-Dist: requests>=2.31.0
Requires-Dist: rich>=13.0.0
